rsaitehu/procrustes.py
rsaitehu_procrustes-0.0.1.dist-info/METADATA
rsaitehu_procrustes-0.0.1.dist-info/WHEEL
rsaitehu_procrustes-0.0.1.dist-info/top_level.txt
rsaitehu_procrustes-0.0.1.dist-info/RECORD
