Metadata-Version: 2.1
Name: rsaitehu-procrustes
Version: 0.0.1
Summary: procrustes utilities
Requires-Dist: numpy >=1.22.0
Requires-Dist: scikit-learn >=1.1.3
Requires-Dist: scipy ==1.9.3
